handle_blastn/__init__.py
handle_blastn/__main__.py
handle_blastn/_clines.py
handle_blastn/_progs.py
handle_blastn/_summaries.py
handle_blastn-0.1.4.dist-info/LICENSE.txt
handle_blastn-0.1.4.dist-info/METADATA
handle_blastn-0.1.4.dist-info/WHEEL
handle_blastn-0.1.4.dist-info/top_level.txt
handle_blastn-0.1.4.dist-info/RECORD
