Metadata-Version: 2.1
Name: handle-blastn
Version: 0.1.4
Summary: Handle blastn.
Author-email: Johannes Programming <johannes-programming@posteo.org>
License: The MIT License (MIT)
Project-URL: Source, https://github.com/johannes-programming/handle_blastn
Project-URL: Download, https://pypi.org/project/handle-blastn/#files
Keywords: blastn
Classifier: License :: OSI Approved :: MIT License
Classifier: Programming Language :: Python
Classifier: Programming Language :: Python :: 3
Requires-Python: >=3.11
License-File: LICENSE.txt
Requires-Dist: Bio >=1.6
Requires-Dist: wonderparse >=1.0.2
Requires-Dist: fileunity >=1.0
